{"nodes": [{"id": "authprovider_AuthProvider", "label": "AuthProvider", "file_type": "code", "source_file": "frontend/src/app/AuthProvider.jsx", "source_location": null, "source_url": null, "captured_at": null, "author": null, "contributor": null}], "edges": [{"source": "authprovider_AuthProvider", "target": "authcontext_useAuth", "relation": "implements", "confidence": "EXTRACTED", "confidence_score": 1.0, "source_file": "frontend/src/app/AuthProvider.jsx", "source_location": null, "weight": 1.0}, {"source": "authprovider_AuthProvider", "target": "supabase_supabase", "relation": "calls", "confidence": "EXTRACTED", "confidence_score": 1.0, "source_file": "frontend/src/app/AuthProvider.jsx", "source_location": null, "weight": 1.0}], "hyperedges": []}