{"nodes": [{"id": "summaryPreview_SummaryPreview", "label": "SummaryPreview", "file_type": "code", "source_file": "frontend/src/pages/SummaryPreview.jsx", "source_location": null, "source_url": null, "captured_at": null, "author": null, "contributor": null}], "edges": [{"source": "summaryPreview_SummaryPreview", "target": "mockData_DEVICES", "relation": "semantically_similar_to", "confidence": "INFERRED", "confidence_score": 0.75, "source_file": "frontend/src/pages/SummaryPreview.jsx", "source_location": null, "weight": 1.0}], "hyperedges": []}